{"errors":[],"warnings":[],"namedChunkGroups":{"app":{"chunks":[5,0,2],"assets":["webpack-runtime-f43ed7f59a14215bcab6.js","webpack-runtime-f43ed7f59a14215bcab6.js.map","commons-46207d72e1342fcaa565.js","commons-46207d72e1342fcaa565.js.map","app-34fc711eef41a66440cb.js","app-34fc711eef41a66440cb.js.map"],"children":{},"childAssets":{}},"component---src-pages-404-js":{"chunks":[1,0,3],"assets":["styles.b50cea7f8d6138c7408b.css","styles-791f37b550a72a598d23.js","styles-791f37b550a72a598d23.js.map","commons-46207d72e1342fcaa565.js","commons-46207d72e1342fcaa565.js.map","component---src-pages-404-js-0290f163286959b63491.js","component---src-pages-404-js-0290f163286959b63491.js.map"],"children":{},"childAssets":{}},"component---src-pages-index-js":{"chunks":[1,0,4],"assets":["styles.b50cea7f8d6138c7408b.css","styles-791f37b550a72a598d23.js","styles-791f37b550a72a598d23.js.map","commons-46207d72e1342fcaa565.js","commons-46207d72e1342fcaa565.js.map","component---src-pages-index-js-0563e066fa1a62f5e344.js","component---src-pages-index-js-0563e066fa1a62f5e344.js.map"],"children":{},"childAssets":{}}},"assetsByChunkName":{"app":["webpack-runtime-f43ed7f59a14215bcab6.js","commons-46207d72e1342fcaa565.js","app-34fc711eef41a66440cb.js"],"component---src-pages-404-js":["styles.b50cea7f8d6138c7408b.css","styles-791f37b550a72a598d23.js","commons-46207d72e1342fcaa565.js","component---src-pages-404-js-0290f163286959b63491.js"],"component---src-pages-index-js":["styles.b50cea7f8d6138c7408b.css","styles-791f37b550a72a598d23.js","commons-46207d72e1342fcaa565.js","component---src-pages-index-js-0563e066fa1a62f5e344.js"]}}